MANIFEST.in
README.md
requirements.txt
setup.py
version.txt
./src/rfc3339.c
scripts/bench_udatetime.py
test/test_udatetime.py
udatetime/__init__.py
udatetime/_pure.py
udatetime.egg-info/PKG-INFO
udatetime.egg-info/SOURCES.txt
udatetime.egg-info/dependency_links.txt
udatetime.egg-info/not-zip-safe
udatetime.egg-info/top_level.txt